chroma_editor/__init__.py
chroma_editor/app.py
chroma_editor/pagination.py
chroma_editor/runner.py
chroma_editor/search_utils.py
chroma_editor-0.1.1.dist-info/METADATA
chroma_editor-0.1.1.dist-info/WHEEL
chroma_editor-0.1.1.dist-info/entry_points.txt
chroma_editor-0.1.1.dist-info/top_level.txt
chroma_editor-0.1.1.dist-info/RECORD
